{
    "returndatacopy" : {
        "_info" : {
            "comment" : "",
            "filling-rpc-server" : "evmone-t8n 0.12.0-dev+commit.364a4c66.dirty",
            "filling-tool-version" : "retesteth-0.3.2-cancun+commit.b50bbe2e.Linux.g++",
            "generatedTestHash" : "703b0577a9fa41b69e91e4056547b181b41ae30ee5db4ad344e601416162dcfa",
            "lllcversion" : "Version: 0.5.14-develop.2022.4.6+commit.401d5358.Linux.g++",
            "solidity" : "Version: 0.8.25+commit.b61c2a91.Linux.g++",
            "source" : "src/EIPTestsFiller/StateTests/stEOF/eof_calls/returndatacopy_Copier.json",
            "sourceHash" : "2fe678ab1e80ade7395eb5edd272fce6f2d88e3ee5477316c4db112af7a32fbc"
        },
        "env" : {
            "currentBaseFee" : "0x3e7",
            "currentCoinbase" : "0x00000000000000000000000000000000c014bace",
            "currentGasLimit" : "0xf4240",
            "currentNumber" : "0x1",
            "currentTimestamp" : "0x1"
        },
        "post" : {
            "Prague" : [
                {
                    "hash" : "0x28fe316b806e34e678e2d9217fba8559ae5f3e8f129a41a009507c71ee8e3bd9",
                    "indexes" : {
                        "data" : 0,
                        "gas" : 0,
                        "value" : 0
                    },
                    "logs" : "0x1dcc4de8dec75d7aab85b567b6ccd41ad312451b948a7413f0a142fd40d49347"
                }
            ]
        },
        "pre" : {
            "0x000000000000000000000000000000000000c0de" : {
                "balance" : "0x0",
                "code" : "0xef00010100040200010028040000000080000460006000730000000000000000000000000000000000ca11eef96020600060003e60005160015500",
                "nonce" : "0x0",
                "storage" : {
                    "0x1" : "0xdd"
                }
            },
            "0x0000000000000000000000000000000000ca11ee" : {
                "balance" : "0x0",
                "code" : "0xef0001010004020001002904000000008000027f497f3c9f61479c1cfa53f0373d39d2bf4e5f73f71411da62f1d6b85c03a6073560005260206000f3",
                "nonce" : "0x0",
                "storage" : {
                }
            },
            "0xa94f5374fce5edbc8e2a8697c15331677e6ebf0b" : {
                "balance" : "0x3b9aca01",
                "code" : "0x",
                "nonce" : "0x1",
                "storage" : {
                }
            }
        },
        "transaction" : {
            "accessLists" : [
                [
                ]
            ],
            "data" : [
                "0x"
            ],
            "gasLimit" : [
                "0xf4240"
            ],
            "maxFeePerGas" : "0x3e8",
            "maxPriorityFeePerGas" : "0x3e8",
            "nonce" : "0x1",
            "secretKey" : "0x45a915e4d060149eb4365960e6a7a45f334393093061116b197e3240065ff2d8",
            "sender" : "0xa94f5374fce5edbc8e2a8697c15331677e6ebf0b",
            "to" : "0x000000000000000000000000000000000000c0de",
            "value" : [
                "0x0"
            ]
        }
    }
}