{
    "variedContext" : {
        "_info" : {
            "comment" : "Ori Pomerantz qbzzt1@gmail.com",
            "filling-rpc-server" : "evm version 1.10.0-unstable",
            "filling-tool-version" : "retesteth-0.1.0-accesslist+commit.f179d53b.Linux.g++",
            "lllcversion" : "Version: 0.5.14-develop.2021.2.24+commit.9189ad7a.Linux.g++",
            "source" : "src/GeneralStateTestsFiller/stEIP2930/variedContextFiller.yml",
            "sourceHash" : "753d68227fb87a1b551f6e53b19bd207e812f1e18e05dd33366fe8111aba9a61",
            "labels" : {
                "0" : ":label delegateCallerInAccessList",
                "1" : ":label delegateCalleeInAccessList",
                "10" : ":label callWriteSuicideValid",
                "11" : ":label callWriteSuicideInvalid",
                "12" : ":label callReadSuicideValid",
                "13" : ":label callReadSuicideInvalid",
                "14" : ":label staticWriteInvalid",
                "15" : ":label staticWriteValid",
                "16" : ":label writeValidGas",
                "17" : ":label writeInvalidOOG",
                "18" : ":label readValidGas",
                "19" : ":label readInvalidOOG",
                "2" : ":label callcodeCallerInAccessList",
                "20" : ":label recurseValid",
                "21" : ":label recurseInvalid",
                "22" : ":label createValid",
                "23" : ":label createInvalid",
                "24" : ":label create2Valid",
                "25" : ":label create2Invalid",
                "26" : ":label callCreatedValid",
                "27" : ":label callCreatedInvalid",
                "28" : ":label callCreate2edValid",
                "29" : ":label callCreate2edInvalid",
                "3" : ":label callcodeCalleeInAccessList",
                "30" : ":label createAndCallValid",
                "31" : ":label createAndCallInvalid",
                "32" : ":label create2AndCallValid",
                "33" : ":label create2AndCallInvalid",
                "34" : ":label callTwiceValid",
                "35" : ":label callTwiceInvalid",
                "4" : ":label callCallerInAccessList",
                "5" : ":label callCalleeInAccessList",
                "6" : ":label staticcallCallerInAccessList",
                "7" : ":label staticcallCalleeInAccessList",
                "8" : ":label callRevertCalleeInAccessList",
                "9" : ":label callRevertCallerInAccessList"
            }
        },
        "env" : {
            "currentCoinbase" : "0x2adc25665018aa1fe0e6bc666dac8fc2697ff9ba",
            "currentDifficulty" : "0x020000",
            "currentGasLimit" : "0xff112233445566",
            "currentNumber" : "0x01",
            "currentTimestamp" : "0x03e8",
            "previousHash" : "0x5e20a0453cecd065ea59c37ac63e079ee08998b6045136a8ce6635c7912ec0b6"
        },
        "post" : {
            "Berlin" : [
                {
                    "indexes" : {
                        "data" : 0,
                        "gas" : 0,
                        "value" : 0
                    },
                    "hash" : "0xceb4826676969bd65c51dde0f5bda6e024457b4cd1223ac8ee6f7a253052b342",
                    "logs" : "0x1dcc4de8dec75d7aab85b567b6ccd41ad312451b948a7413f0a142fd40d49347"
                },
                {
                    "indexes" : {
                        "data" : 1,
                        "gas" : 0,
                        "value" : 0
                    },
                    "hash" : "0xdfd1f1fb1de206060703bcff5347e7274c950ed112c0db07fc61589391eacc82",
                    "logs" : "0x1dcc4de8dec75d7aab85b567b6ccd41ad312451b948a7413f0a142fd40d49347"
                },
                {
                    "indexes" : {
                        "data" : 2,
                        "gas" : 0,
                        "value" : 0
                    },
                    "hash" : "0xa2f264bdbc4ad61b2b5b2e5dcb57e380f7d7fc5e384126882075a87604ce0bf3",
                    "logs" : "0x1dcc4de8dec75d7aab85b567b6ccd41ad312451b948a7413f0a142fd40d49347"
                },
                {
                    "indexes" : {
                        "data" : 3,
                        "gas" : 0,
                        "value" : 0
                    },
                    "hash" : "0x3276ccc4ba50d23adf175a6db160a20de1093460ad8c7ec9cf0e19ccbe91e899",
                    "logs" : "0x1dcc4de8dec75d7aab85b567b6ccd41ad312451b948a7413f0a142fd40d49347"
                },
                {
                    "indexes" : {
                        "data" : 4,
                        "gas" : 0,
                        "value" : 0
                    },
                    "hash" : "0x38b2fcd424e40b4497ef14088543e7d1b1c4cd1575bc203d025aa40eca7bcd8d",
                    "logs" : "0x1dcc4de8dec75d7aab85b567b6ccd41ad312451b948a7413f0a142fd40d49347"
                },
                {
                    "indexes" : {
                        "data" : 5,
                        "gas" : 0,
                        "value" : 0
                    },
                    "hash" : "0xd40825597edf5c3fb4c782f71e9c98e115931adf550a8f8a4c31de1db49dbb39",
                    "logs" : "0x1dcc4de8dec75d7aab85b567b6ccd41ad312451b948a7413f0a142fd40d49347"
                },
                {
                    "indexes" : {
                        "data" : 6,
                        "gas" : 0,
                        "value" : 0
                    },
                    "hash" : "0xa67439f96ee3d2f9e910fc56ef7cf88bfba701297cdeeb5764df9d9ec29edf20",
                    "logs" : "0x1dcc4de8dec75d7aab85b567b6ccd41ad312451b948a7413f0a142fd40d49347"
                },
                {
                    "indexes" : {
                        "data" : 7,
                        "gas" : 0,
                        "value" : 0
                    },
                    "hash" : "0xa82dced50c976c5889a676b5fdf180ef90d38cede2601d5b3cafbf439cd5bea4",
                    "logs" : "0x1dcc4de8dec75d7aab85b567b6ccd41ad312451b948a7413f0a142fd40d49347"
                },
                {
                    "indexes" : {
                        "data" : 8,
                        "gas" : 0,
                        "value" : 0
                    },
                    "hash" : "0xbb8dd1a7530e8b45fef8f8eb2e7f18620c75e938a27019262df5e5682516aff4",
                    "logs" : "0x1dcc4de8dec75d7aab85b567b6ccd41ad312451b948a7413f0a142fd40d49347"
                },
                {
                    "indexes" : {
                        "data" : 9,
                        "gas" : 0,
                        "value" : 0
                    },
                    "hash" : "0xdc77e08928d1472fc90195a72ca485ca2185e102fc3adbb9e22669bbf546c2ec",
                    "logs" : "0x1dcc4de8dec75d7aab85b567b6ccd41ad312451b948a7413f0a142fd40d49347"
                },
                {
                    "indexes" : {
                        "data" : 10,
                        "gas" : 0,
                        "value" : 0
                    },
                    "hash" : "0x2f91d9d7f09f7391e734a9bdad8f7ec0fa89c04351399d2b9551bf5141537bce",
                    "logs" : "0x1dcc4de8dec75d7aab85b567b6ccd41ad312451b948a7413f0a142fd40d49347"
                },
                {
                    "indexes" : {
                        "data" : 11,
                        "gas" : 0,
                        "value" : 0
                    },
                    "hash" : "0x0910b98db26e83f26ee6f7dc7ac668460f58f9a1374ac953a31081573ed056ce",
                    "logs" : "0x1dcc4de8dec75d7aab85b567b6ccd41ad312451b948a7413f0a142fd40d49347"
                },
                {
                    "indexes" : {
                        "data" : 12,
                        "gas" : 0,
                        "value" : 0
                    },
                    "hash" : "0xdb32e3c740cfc11a37c110c53c50eb6933e3f1036e960ce4e464f814f2ca9a12",
                    "logs" : "0x1dcc4de8dec75d7aab85b567b6ccd41ad312451b948a7413f0a142fd40d49347"
                },
                {
                    "indexes" : {
                        "data" : 13,
                        "gas" : 0,
                        "value" : 0
                    },
                    "hash" : "0x143a4d0a9b2aedb5e32030608e497f6a2db87bdb78e0b32356c7c501cf8a3e04",
                    "logs" : "0x1dcc4de8dec75d7aab85b567b6ccd41ad312451b948a7413f0a142fd40d49347"
                },
                {
                    "indexes" : {
                        "data" : 14,
                        "gas" : 0,
                        "value" : 0
                    },
                    "hash" : "0x63915428828cdfde234e9cf1b09c748144ca40eb9cc75b7221a5babe630ec1ae",
                    "logs" : "0x1dcc4de8dec75d7aab85b567b6ccd41ad312451b948a7413f0a142fd40d49347"
                },
                {
                    "indexes" : {
                        "data" : 15,
                        "gas" : 0,
                        "value" : 0
                    },
                    "hash" : "0x7b8cc0c385ad3dd345e8461f5cc62d1cd08100850de3cffec71ab2796df28a9c",
                    "logs" : "0x1dcc4de8dec75d7aab85b567b6ccd41ad312451b948a7413f0a142fd40d49347"
                },
                {
                    "indexes" : {
                        "data" : 16,
                        "gas" : 0,
                        "value" : 0
                    },
                    "hash" : "0x9d7db3b9cc77cbda5f57ceb20d8aa6599f9374df3b8c62dacf13711a47207306",
                    "logs" : "0x1dcc4de8dec75d7aab85b567b6ccd41ad312451b948a7413f0a142fd40d49347"
                },
                {
                    "indexes" : {
                        "data" : 17,
                        "gas" : 0,
                        "value" : 0
                    },
                    "hash" : "0xbb498048dd31618f137e82b47e10f8406ad6636ac155700ab19c332789f55801",
                    "logs" : "0x1dcc4de8dec75d7aab85b567b6ccd41ad312451b948a7413f0a142fd40d49347"
                },
                {
                    "indexes" : {
                        "data" : 18,
                        "gas" : 0,
                        "value" : 0
                    },
                    "hash" : "0xe7c34e9ebc1c8a1991d0e544000a53821f74e3d1167cd1a8492c22bb20cf5c2d",
                    "logs" : "0x1dcc4de8dec75d7aab85b567b6ccd41ad312451b948a7413f0a142fd40d49347"
                },
                {
                    "indexes" : {
                        "data" : 19,
                        "gas" : 0,
                        "value" : 0
                    },
                    "hash" : "0x5cf461954adcd598d345ec419c16d51dd0a7594a0d80d93c4ae6f5c951e6511d",
                    "logs" : "0x1dcc4de8dec75d7aab85b567b6ccd41ad312451b948a7413f0a142fd40d49347"
                },
                {
                    "indexes" : {
                        "data" : 20,
                        "gas" : 0,
                        "value" : 0
                    },
                    "hash" : "0x89559c46ff2ff60bea5712ad9889a82cb257640745e637edab7ced55f1adef7d",
                    "logs" : "0x1dcc4de8dec75d7aab85b567b6ccd41ad312451b948a7413f0a142fd40d49347"
                },
                {
                    "indexes" : {
                        "data" : 21,
                        "gas" : 0,
                        "value" : 0
                    },
                    "hash" : "0x3e41a61ebae481c33e1a0ff6a8259db00dd55992e23219260480d8a1f576bdfb",
                    "logs" : "0x1dcc4de8dec75d7aab85b567b6ccd41ad312451b948a7413f0a142fd40d49347"
                },
                {
                    "indexes" : {
                        "data" : 22,
                        "gas" : 0,
                        "value" : 0
                    },
                    "hash" : "0xad4c23f881b05ca0d00f8a9bdbafa95aac99275b1338ea1b7e2b9dcd88a9c4ba",
                    "logs" : "0x1dcc4de8dec75d7aab85b567b6ccd41ad312451b948a7413f0a142fd40d49347"
                },
                {
                    "indexes" : {
                        "data" : 23,
                        "gas" : 0,
                        "value" : 0
                    },
                    "hash" : "0xcfb89a4ca81cfa20e046b82ae53785c11329d4fba889fc91bcd7c7ef209dfd59",
                    "logs" : "0x1dcc4de8dec75d7aab85b567b6ccd41ad312451b948a7413f0a142fd40d49347"
                },
                {
                    "indexes" : {
                        "data" : 24,
                        "gas" : 0,
                        "value" : 0
                    },
                    "hash" : "0x97ab8a0ac5b179d3d24d827599e4a21dc26e42848cea0561769a91c8b0a3968e",
                    "logs" : "0x1dcc4de8dec75d7aab85b567b6ccd41ad312451b948a7413f0a142fd40d49347"
                },
                {
                    "indexes" : {
                        "data" : 25,
                        "gas" : 0,
                        "value" : 0
                    },
                    "hash" : "0xc2f7bf6421e2fee67565e91ee1374ab6c254928961a3ec35d44bc532e42bc534",
                    "logs" : "0x1dcc4de8dec75d7aab85b567b6ccd41ad312451b948a7413f0a142fd40d49347"
                },
                {
                    "indexes" : {
                        "data" : 26,
                        "gas" : 0,
                        "value" : 0
                    },
                    "hash" : "0xb02d25ca78ff911aa575812aa9711b15ed072b84a5a4a4313a73caf440f8614e",
                    "logs" : "0x1dcc4de8dec75d7aab85b567b6ccd41ad312451b948a7413f0a142fd40d49347"
                },
                {
                    "indexes" : {
                        "data" : 27,
                        "gas" : 0,
                        "value" : 0
                    },
                    "hash" : "0x5528bfec39880ca06bb5b5af512158717346aded1c8e62bb40a054b165eb2004",
                    "logs" : "0x1dcc4de8dec75d7aab85b567b6ccd41ad312451b948a7413f0a142fd40d49347"
                },
                {
                    "indexes" : {
                        "data" : 28,
                        "gas" : 0,
                        "value" : 0
                    },
                    "hash" : "0x83079862899309affa839399ef522e53e848d62364ede4a846be8bd09e7a4830",
                    "logs" : "0x1dcc4de8dec75d7aab85b567b6ccd41ad312451b948a7413f0a142fd40d49347"
                },
                {
                    "indexes" : {
                        "data" : 29,
                        "gas" : 0,
                        "value" : 0
                    },
                    "hash" : "0x123272b1ec60707c94746841992c64dd24d63c8557f5a8e7192f9580d04a11e4",
                    "logs" : "0x1dcc4de8dec75d7aab85b567b6ccd41ad312451b948a7413f0a142fd40d49347"
                },
                {
                    "indexes" : {
                        "data" : 30,
                        "gas" : 0,
                        "value" : 0
                    },
                    "hash" : "0xece54c57e6e9159c4386e5b145aebb9af644e795ee75950dd30fb14147afcaec",
                    "logs" : "0x1dcc4de8dec75d7aab85b567b6ccd41ad312451b948a7413f0a142fd40d49347"
                },
                {
                    "indexes" : {
                        "data" : 31,
                        "gas" : 0,
                        "value" : 0
                    },
                    "hash" : "0x31b28fd7d7a7560d9bc883d6458552b399e99170167a7c0cfe09a8bd2cfde1cf",
                    "logs" : "0x1dcc4de8dec75d7aab85b567b6ccd41ad312451b948a7413f0a142fd40d49347"
                },
                {
                    "indexes" : {
                        "data" : 32,
                        "gas" : 0,
                        "value" : 0
                    },
                    "hash" : "0x5b22aacfd1298e2bba2a751de8a3d3e52796ff14591a87fe258f2bcaaf5bfe77",
                    "logs" : "0x1dcc4de8dec75d7aab85b567b6ccd41ad312451b948a7413f0a142fd40d49347"
                },
                {
                    "indexes" : {
                        "data" : 33,
                        "gas" : 0,
                        "value" : 0
                    },
                    "hash" : "0xba462f8a570cc5278ba95ea4be16030a222e09fa748183d3c03748f74793e883",
                    "logs" : "0x1dcc4de8dec75d7aab85b567b6ccd41ad312451b948a7413f0a142fd40d49347"
                },
                {
                    "indexes" : {
                        "data" : 34,
                        "gas" : 0,
                        "value" : 0
                    },
                    "hash" : "0x08fdf32a2202556b79890a267409f313be7a6b2afa697bfe06bbcbce95819752",
                    "logs" : "0x1dcc4de8dec75d7aab85b567b6ccd41ad312451b948a7413f0a142fd40d49347"
                },
                {
                    "indexes" : {
                        "data" : 35,
                        "gas" : 0,
                        "value" : 0
                    },
                    "hash" : "0xc0fbee353996c0e923521a0848cbcdd0a94bd49e601181cdf622651399826e4b",
                    "logs" : "0x1dcc4de8dec75d7aab85b567b6ccd41ad312451b948a7413f0a142fd40d49347"
                }
            ]
        },
        "pre" : {
            "0x0000000000000000000000000000000000000100" : {
                "balance" : "0x0de0b6b3a7640000",
                "code" : "0x600060006000600061c0575af400",
                "nonce" : "0x00",
                "storage" : {
                }
            },
            "0x0000000000000000000000000000000000000101" : {
                "balance" : "0x0de0b6b3a7640000",
                "code" : "0x6000600060006000600061c0575af100",
                "nonce" : "0x00",
                "storage" : {
                }
            },
            "0x0000000000000000000000000000000000000102" : {
                "balance" : "0x0de0b6b3a7640000",
                "code" : "0x6000600060006000600061c0575af200",
                "nonce" : "0x00",
                "storage" : {
                }
            },
            "0x0000000000000000000000000000000000000103" : {
                "balance" : "0x0de0b6b3a7640000",
                "code" : "0x602060006000600063ead0c0575afa5060005160005500",
                "nonce" : "0x00",
                "storage" : {
                }
            },
            "0x0000000000000000000000000000000000000110" : {
                "balance" : "0x0de0b6b3a7640000",
                "code" : "0x5a600052600260005560115a60005103036000525a6020526160a754604052601a5a602051030360205260406000fd00",
                "nonce" : "0x00",
                "storage" : {
                    "0x60a7" : "0xbeef"
                }
            },
            "0x0000000000000000000000000000000000000111" : {
                "balance" : "0x0de0b6b3a7640000",
                "code" : "0x5a6000526000600060006000600063dead01115af150617fe85a600051030360005500",
                "nonce" : "0x00",
                "storage" : {
                }
            },
            "0x0000000000000000000000000000000000000112" : {
                "balance" : "0x0de0b6b3a7640000",
                "code" : "0x5a6000526000600060006000600063dead01125af150617fe85a600051030360005500",
                "nonce" : "0x00",
                "storage" : {
                }
            },
            "0x0000000000000000000000000000000000000113" : {
                "balance" : "0x0de0b6b3a7640000",
                "code" : "0x610bad600052602060006000600061f1135afa5060005160005500",
                "nonce" : "0x00",
                "storage" : {
                    "0x00" : "0x60a7"
                }
            },
            "0x0000000000000000000000000000000000000114" : {
                "balance" : "0x0de0b6b3a7640000",
                "code" : "0x6020600060006000600061f114610b65f100",
                "nonce" : "0x00",
                "storage" : {
                }
            },
            "0x0000000000000000000000000000000000000115" : {
                "balance" : "0x0de0b6b3a7640000",
                "code" : "0x6020600060006000600061f115611800f100",
                "nonce" : "0x00",
                "storage" : {
                }
            },
            "0x0000000000000000000000000000000000000116" : {
                "balance" : "0x0de0b6b3a7640000",
                "code" : "0x600054505a600052600261beef5560115a60005103036000525a6020526160a75460a05260235a60205103036020525a60405261beef60005461f000015560785a60405103036040525a60605260005461f010015450607a5a60605103036060526000516000546101000155602051600054610200015560405160005461030001556060516000546104000155600060005411609b57600060b4565b600160005403600055600060006000600060006101165af15b00",
                "nonce" : "0x00",
                "storage" : {
                    "0x00" : "0x0f",
                    "0x60a7" : "0xdead"
                }
            },
            "0x0000000000000000000000000000000000000120" : {
                "balance" : "0x0ba1a9ce0ba1a9ce",
                "code" : "0x60068060336101003961020052602180603960003961022052610200516101000160006000f0610240526102405160015500fe60ff600055005a60005261ffff6000555a6000510360015561010061010060003960106000f300",
                "nonce" : "0x00",
                "storage" : {
                }
            },
            "0x0000000000000000000000000000000000000121" : {
                "balance" : "0x0ba1a9ce0ba1a9ce",
                "code" : "0x60068060366101003961020052602180603c60003961022052615a17610200516101000160006000f5610240526102405160015500fe60ff600055005a60005261ffff6000555a6000510360015561010061010060003960106000f300",
                "nonce" : "0x00",
                "storage" : {
                }
            },
            "0x0000000000000000000000000000000000000122" : {
                "balance" : "0x0ba1a9ce0ba1a9ce",
                "code" : "0x60138060446101003961020052600f80605760003961022052610200516101000160006000f06102405260006000600060006000610240515af1506102405160015500fe5a60005261ffff6000555a600051036001550061010061010060003960806000f300",
                "nonce" : "0x00",
                "storage" : {
                }
            },
            "0x0000000000000000000000000000000000000123" : {
                "balance" : "0x0ba1a9ce0ba1a9ce",
                "code" : "0x60138060476101003961020052600f80605a60003961022052615a17610200516101000160006000f56102405260006000600060006000610240515af1506102405160015500fe5a60005261ffff6000555a600051036001550061010061010060003960806000f300",
                "nonce" : "0x00",
                "storage" : {
                }
            },
            "0x0000000000000000000000000000000000000124" : {
                "balance" : "0x0ba1a9ce0ba1a9ce",
                "code" : "0x60138060446101003961020052602180605760003961022052610200516101000160006000f06102405260006000600060006000610240515af1506102405160015500fe5a60005261ffff6000555a60005103600255005a60005261ffff6000555a6000510360015561010061010060003960806000f300",
                "nonce" : "0x00",
                "storage" : {
                }
            },
            "0x0000000000000000000000000000000000000125" : {
                "balance" : "0x0ba1a9ce0ba1a9ce",
                "code" : "0x60138060476101003961020052602180605a60003961022052615a17610200516101000160006000f56102405260006000600060006000610240515af1506102405160015500fe5a60005261ffff6000555a60005103600255005a60005261ffff6000555a6000510360015561010061010060003960806000f300",
                "nonce" : "0x00",
                "storage" : {
                }
            },
            "0x0000000000000000000000000000000000000126" : {
                "balance" : "0x0ba1a9ce0ba1a9ce",
                "code" : "0x6000600060006000600061f1265af1506000600060006000600061f1265af100",
                "nonce" : "0x00",
                "storage" : {
                }
            },
            "0x000000000000000000000000000000000000c057" : {
                "balance" : "0x0de0b6b3a7640000",
                "code" : "0x5a600052600260005560115a60005103036000526000516001555a6000526160a75460205260105a600051030360005260005160025500",
                "nonce" : "0x00",
                "storage" : {
                    "0x60a7" : "0xdead"
                }
            },
            "0x000000000000000000000000000000000000f113" : {
                "balance" : "0x0de0b6b3a7640000",
                "code" : "0x63dead60a760005561600d60005260206000f300",
                "nonce" : "0x00",
                "storage" : {
                }
            },
            "0x000000000000000000000000000000000000f114" : {
                "balance" : "0x0de0b6b3a7640000",
                "code" : "0x61600d60005500",
                "nonce" : "0x00",
                "storage" : {
                    "0x00" : "0x0bad"
                }
            },
            "0x000000000000000000000000000000000000f115" : {
                "balance" : "0x0de0b6b3a7640000",
                "code" : "0x6160a75460005261600d60005500",
                "nonce" : "0x00",
                "storage" : {
                    "0x00" : "0x0bad",
                    "0x60a7" : "0xdead"
                }
            },
            "0x000000000000000000000000000000000000f126" : {
                "balance" : "0x0ba1a9ce0ba1a9ce",
                "code" : "0x5a6000526160a76000555a60005103600052600060015414602457600051600255602b565b6000516001555b00",
                "nonce" : "0x00",
                "storage" : {
                }
            },
            "0x00000000000000000000000000000000dead0111" : {
                "balance" : "0x0de0b6b3a7640000",
                "code" : "0x61dead6000556000ff00",
                "nonce" : "0x00",
                "storage" : {
                }
            },
            "0x00000000000000000000000000000000dead0112" : {
                "balance" : "0x0de0b6b3a7640000",
                "code" : "0x600054506000ff00",
                "nonce" : "0x00",
                "storage" : {
                    "0x00" : "0xdead0060a7"
                }
            },
            "0x00000000000000000000000000000000ead0c057" : {
                "balance" : "0x0de0b6b3a7640000",
                "code" : "0x5a6000526160a75460205260135a600051030360005260206000f300",
                "nonce" : "0x00",
                "storage" : {
                    "0x60a7" : "0xdead"
                }
            },
            "0xa94f5374fce5edbc8e2a8697c15331677e6ebf0b" : {
                "balance" : "0x0de0b6b3a7640000",
                "code" : "0x",
                "nonce" : "0x00",
                "storage" : {
                }
            },
            "0xcccccccccccccccccccccccccccccccccccccccc" : {
                "balance" : "0x00",
                "code" : "0x60406000600060006000600435610100015af15060005160005560205160015500",
                "nonce" : "0x00",
                "storage" : {
                }
            }
        },
        "transaction" : {
            "data" : [
                "0x693c61390000000000000000000000000000000000000000000000000000000000000000",
                "0x693c61390000000000000000000000000000000000000000000000000000000000000000",
                "0x693c61390000000000000000000000000000000000000000000000000000000000000002",
                "0x693c61390000000000000000000000000000000000000000000000000000000000000002",
                "0x693c61390000000000000000000000000000000000000000000000000000000000000001",
                "0x693c61390000000000000000000000000000000000000000000000000000000000000001",
                "0x693c61390000000000000000000000000000000000000000000000000000000000000003",
                "0x693c61390000000000000000000000000000000000000000000000000000000000000003",
                "0x693c61390000000000000000000000000000000000000000000000000000000000000010",
                "0x693c61390000000000000000000000000000000000000000000000000000000000000010",
                "0x693c61390000000000000000000000000000000000000000000000000000000000000011",
                "0x693c61390000000000000000000000000000000000000000000000000000000000000011",
                "0x693c61390000000000000000000000000000000000000000000000000000000000000012",
                "0x693c61390000000000000000000000000000000000000000000000000000000000000012",
                "0x693c61390000000000000000000000000000000000000000000000000000000000000013",
                "0x693c61390000000000000000000000000000000000000000000000000000000000000013",
                "0x693c61390000000000000000000000000000000000000000000000000000000000000014",
                "0x693c61390000000000000000000000000000000000000000000000000000000000000014",
                "0x693c61390000000000000000000000000000000000000000000000000000000000000015",
                "0x693c61390000000000000000000000000000000000000000000000000000000000000015",
                "0x693c61390000000000000000000000000000000000000000000000000000000000000016",
                "0x693c61390000000000000000000000000000000000000000000000000000000000000016",
                "0x693c61390000000000000000000000000000000000000000000000000000000000000020",
                "0x693c61390000000000000000000000000000000000000000000000000000000000000020",
                "0x693c61390000000000000000000000000000000000000000000000000000000000000021",
                "0x693c61390000000000000000000000000000000000000000000000000000000000000021",
                "0x693c61390000000000000000000000000000000000000000000000000000000000000022",
                "0x693c61390000000000000000000000000000000000000000000000000000000000000022",
                "0x693c61390000000000000000000000000000000000000000000000000000000000000023",
                "0x693c61390000000000000000000000000000000000000000000000000000000000000023",
                "0x693c61390000000000000000000000000000000000000000000000000000000000000024",
                "0x693c61390000000000000000000000000000000000000000000000000000000000000024",
                "0x693c61390000000000000000000000000000000000000000000000000000000000000025",
                "0x693c61390000000000000000000000000000000000000000000000000000000000000025",
                "0x693c61390000000000000000000000000000000000000000000000000000000000000026",
                "0x693c61390000000000000000000000000000000000000000000000000000000000000026"
            ],
            "accessLists" : [
                [
                    {
                        "address" : "0x0000000000000000000000000000000000000100",
                        "storageKeys" : [
                            "0x0000000000000000000000000000000000000000000000000000000000000000",
                            "0x00000000000000000000000000000000000000000000000000000000000060a7"
                        ]
                    }
                ],
                [
                    {
                        "address" : "0x000000000000000000000000000000000000c057",
                        "storageKeys" : [
                            "0x0000000000000000000000000000000000000000000000000000000000000000",
                            "0x00000000000000000000000000000000000000000000000000000000000060a7"
                        ]
                    }
                ],
                [
                    {
                        "address" : "0x0000000000000000000000000000000000000102",
                        "storageKeys" : [
                            "0x0000000000000000000000000000000000000000000000000000000000000000",
                            "0x00000000000000000000000000000000000000000000000000000000000060a7"
                        ]
                    }
                ],
                [
                    {
                        "address" : "0x000000000000000000000000000000000000c057",
                        "storageKeys" : [
                            "0x0000000000000000000000000000000000000000000000000000000000000000",
                            "0x00000000000000000000000000000000000000000000000000000000000060a7"
                        ]
                    }
                ],
                [
                    {
                        "address" : "0x0000000000000000000000000000000000000101",
                        "storageKeys" : [
                            "0x0000000000000000000000000000000000000000000000000000000000000000",
                            "0x00000000000000000000000000000000000000000000000000000000000060a7"
                        ]
                    }
                ],
                [
                    {
                        "address" : "0x000000000000000000000000000000000000c057",
                        "storageKeys" : [
                            "0x0000000000000000000000000000000000000000000000000000000000000000",
                            "0x00000000000000000000000000000000000000000000000000000000000060a7"
                        ]
                    }
                ],
                [
                    {
                        "address" : "0x0000000000000000000000000000000000000103",
                        "storageKeys" : [
                            "0x0000000000000000000000000000000000000000000000000000000000000000",
                            "0x00000000000000000000000000000000000000000000000000000000000060a7"
                        ]
                    }
                ],
                [
                    {
                        "address" : "0x00000000000000000000000000000000ead0c057",
                        "storageKeys" : [
                            "0x0000000000000000000000000000000000000000000000000000000000000000",
                            "0x00000000000000000000000000000000000000000000000000000000000060a7"
                        ]
                    }
                ],
                [
                    {
                        "address" : "0x0000000000000000000000000000000000000110",
                        "storageKeys" : [
                            "0x0000000000000000000000000000000000000000000000000000000000000000",
                            "0x00000000000000000000000000000000000000000000000000000000000060a7"
                        ]
                    }
                ],
                [
                    {
                        "address" : "0xcccccccccccccccccccccccccccccccccccccccc",
                        "storageKeys" : [
                            "0x0000000000000000000000000000000000000000000000000000000000000000",
                            "0x00000000000000000000000000000000000000000000000000000000000060a7"
                        ]
                    }
                ],
                [
                    {
                        "address" : "0x00000000000000000000000000000000dead0111",
                        "storageKeys" : [
                            "0x0000000000000000000000000000000000000000000000000000000000000000"
                        ]
                    }
                ],
                [
                    {
                        "address" : "0x0000000000000000000000000000000000000111",
                        "storageKeys" : [
                            "0x0000000000000000000000000000000000000000000000000000000000000000"
                        ]
                    }
                ],
                [
                    {
                        "address" : "0x00000000000000000000000000000000dead0112",
                        "storageKeys" : [
                            "0x0000000000000000000000000000000000000000000000000000000000000000"
                        ]
                    }
                ],
                [
                    {
                        "address" : "0x0000000000000000000000000000000000000112",
                        "storageKeys" : [
                            "0x0000000000000000000000000000000000000000000000000000000000000000"
                        ]
                    }
                ],
                [
                    {
                        "address" : "0x0000000000000000000000000000000000000000",
                        "storageKeys" : [
                            "0x0000000000000000000000000000000000000000000000000000000000000000"
                        ]
                    }
                ],
                [
                    {
                        "address" : "0x000000000000000000000000000000000000f113",
                        "storageKeys" : [
                            "0x0000000000000000000000000000000000000000000000000000000000000000"
                        ]
                    }
                ],
                [
                    {
                        "address" : "0x000000000000000000000000000000000000f114",
                        "storageKeys" : [
                            "0x0000000000000000000000000000000000000000000000000000000000000000"
                        ]
                    }
                ],
                [
                    {
                        "address" : "0x0000000000000000000000000000000000000114",
                        "storageKeys" : [
                            "0x0000000000000000000000000000000000000000000000000000000000000000"
                        ]
                    }
                ],
                [
                    {
                        "address" : "0x000000000000000000000000000000000000f115",
                        "storageKeys" : [
                            "0x00000000000000000000000000000000000000000000000000000000000060a7"
                        ]
                    }
                ],
                [
                    {
                        "address" : "0x0000000000000000000000000000000000000115",
                        "storageKeys" : [
                            "0x00000000000000000000000000000000000000000000000000000000000060a7"
                        ]
                    }
                ],
                [
                    {
                        "address" : "0x0000000000000000000000000000000000000116",
                        "storageKeys" : [
                            "0x00000000000000000000000000000000000000000000000000000000000060a7",
                            "0x000000000000000000000000000000000000000000000000000000000000beef",
                            "0x000000000000000000000000000000000000000000000000000000000000f000",
                            "0x000000000000000000000000000000000000000000000000000000000000f001",
                            "0x000000000000000000000000000000000000000000000000000000000000f002",
                            "0x000000000000000000000000000000000000000000000000000000000000f003",
                            "0x000000000000000000000000000000000000000000000000000000000000f004",
                            "0x000000000000000000000000000000000000000000000000000000000000f005",
                            "0x000000000000000000000000000000000000000000000000000000000000f006",
                            "0x000000000000000000000000000000000000000000000000000000000000f007",
                            "0x000000000000000000000000000000000000000000000000000000000000f008",
                            "0x000000000000000000000000000000000000000000000000000000000000f009",
                            "0x000000000000000000000000000000000000000000000000000000000000f00a",
                            "0x000000000000000000000000000000000000000000000000000000000000f00b",
                            "0x000000000000000000000000000000000000000000000000000000000000f00c",
                            "0x000000000000000000000000000000000000000000000000000000000000f00d",
                            "0x000000000000000000000000000000000000000000000000000000000000f00e",
                            "0x000000000000000000000000000000000000000000000000000000000000f00f",
                            "0x000000000000000000000000000000000000000000000000000000000000f010",
                            "0x000000000000000000000000000000000000000000000000000000000000f011",
                            "0x000000000000000000000000000000000000000000000000000000000000f012",
                            "0x000000000000000000000000000000000000000000000000000000000000f013",
                            "0x000000000000000000000000000000000000000000000000000000000000f014",
                            "0x000000000000000000000000000000000000000000000000000000000000f015",
                            "0x000000000000000000000000000000000000000000000000000000000000f016",
                            "0x000000000000000000000000000000000000000000000000000000000000f017",
                            "0x000000000000000000000000000000000000000000000000000000000000f018",
                            "0x000000000000000000000000000000000000000000000000000000000000f019",
                            "0x000000000000000000000000000000000000000000000000000000000000f01a",
                            "0x000000000000000000000000000000000000000000000000000000000000f01b",
                            "0x000000000000000000000000000000000000000000000000000000000000f01c",
                            "0x000000000000000000000000000000000000000000000000000000000000f01d",
                            "0x000000000000000000000000000000000000000000000000000000000000f01e",
                            "0x000000000000000000000000000000000000000000000000000000000000f01f"
                        ]
                    }
                ],
                [
                    {
                        "address" : "0xf000000000000000000000000000000000000116",
                        "storageKeys" : [
                            "0x00000000000000000000000000000000000000000000000000000000000060a7",
                            "0x000000000000000000000000000000000000000000000000000000000000beef"
                        ]
                    }
                ],
                [
                    {
                        "address" : "0xb3cd7ba32badf538e31cff49e429845e01d02e1e",
                        "storageKeys" : [
                            "0x0000000000000000000000000000000000000000000000000000000000000000"
                        ]
                    }
                ],
                [
                    {
                        "address" : "0xb3cd7ba32badf538e31cff49e429845e01d02e1e",
                        "storageKeys" : [
                            "0x0000000000000000000000000000000000000000000000000000000000000001"
                        ]
                    }
                ],
                [
                    {
                        "address" : "0xb35944ad11333d409963ee803de127444bd75cb2",
                        "storageKeys" : [
                            "0x0000000000000000000000000000000000000000000000000000000000000000"
                        ]
                    }
                ],
                [
                    {
                        "address" : "0xb3cd7ba32badf538e31cff49e429845e01d02e1e",
                        "storageKeys" : [
                            "0x0000000000000000000000000000000000000000000000000000000000000000"
                        ]
                    }
                ],
                [
                    {
                        "address" : "0x9a6f25be6cfe3b81741200d3fa35447380f33b75",
                        "storageKeys" : [
                            "0x0000000000000000000000000000000000000000000000000000000000000000"
                        ]
                    }
                ],
                [
                    {
                        "address" : "0x9a6f25be6cfe3b81741200d3fa35447380f33b75",
                        "storageKeys" : [
                            "0x000000000000000000000000000000000000000000000000000000000000ffff"
                        ]
                    }
                ],
                [
                    {
                        "address" : "0x2602b48c9be257db2b30fb0e65709c05f5ec7b04",
                        "storageKeys" : [
                            "0x0000000000000000000000000000000000000000000000000000000000000000"
                        ]
                    }
                ],
                [
                    {
                        "address" : "0x9a6f25be6cfe3b81741200d3fa35447380f33b75",
                        "storageKeys" : [
                            "0x000000000000000000000000000000000000000000000000000000000000ffff"
                        ]
                    }
                ],
                [
                    {
                        "address" : "0x3325d25f43be85f8f579fb00648a8ce937d87d09",
                        "storageKeys" : [
                            "0x0000000000000000000000000000000000000000000000000000000000000000"
                        ]
                    }
                ],
                [
                    {
                        "address" : "0x9a6f25be6cfe3b81741200d3fa35447380f33b75",
                        "storageKeys" : [
                            "0x000000000000000000000000000000000000000000000000000000000000ffff"
                        ]
                    }
                ],
                [
                    {
                        "address" : "0x1645c3584d9baacc965b0ffa91b33f02f1f5fa0a",
                        "storageKeys" : [
                            "0x0000000000000000000000000000000000000000000000000000000000000000"
                        ]
                    }
                ],
                [
                    {
                        "address" : "0x9a6f25be6cfe3b81741200d3fa35447380f33b75",
                        "storageKeys" : [
                            "0x000000000000000000000000000000000000000000000000000000000000ffff"
                        ]
                    }
                ],
                [
                    {
                        "address" : "0x000000000000000000000000000000000000f126",
                        "storageKeys" : [
                            "0x0000000000000000000000000000000000000000000000000000000000000000"
                        ]
                    }
                ],
                [
                    {
                        "address" : "0x000000000000000000000000000000000000f126",
                        "storageKeys" : [
                            "0x0000000000000000000000000000000000000000000000000000000000000020"
                        ]
                    }
                ]
            ],
            "gasLimit" : [
                "0x02625a00"
            ],
            "gasPrice" : "0x01",
            "nonce" : "0x00",
            "secretKey" : "0x45a915e4d060149eb4365960e6a7a45f334393093061116b197e3240065ff2d8",
            "to" : "0xcccccccccccccccccccccccccccccccccccccccc",
            "value" : [
                "0x0186a0"
            ]
        }
    }
}