{
    "RLPIncorrectByteEncoding00" : {
        "_info" : {
            "comment" : "",
            "filling-rpc-server" : "evm version 1.13.11-unstable-765f2904-20240124",
            "filling-tool-version" : "retesteth-0.3.2-cancun+commit.a95c757e.Linux.g++",
            "generatedTestHash" : "79bb7f0484eb4277c1cf2ca962cc73bd53536612e8982f8fbdec5c9a37ecff9b",
            "lllcversion" : "Version: 0.5.14-develop.2023.7.11+commit.c58ab2c6.mod.Linux.g++",
            "solidity" : "Version: 0.8.21+commit.d9974bed.Linux.g++",
            "source" : "src/TransactionTestsFiller/ttWrongRLP/RLPIncorrectByteEncoding00Copier.json",
            "sourceHash" : "2f5cf32a648e9a3d828a08159c182945c61cb85797b271adc257953c0f47ff01"
        },
        "result" : {
            "Berlin" : {
                "exception" : "LeadingZerosNonceSize",
                "intrinsicGas" : "0x00"
            },
            "Byzantium" : {
                "exception" : "LeadingZerosNonceSize",
                "intrinsicGas" : "0x00"
            },
            "Constantinople" : {
                "exception" : "LeadingZerosNonceSize",
                "intrinsicGas" : "0x00"
            },
            "ConstantinopleFix" : {
                "exception" : "LeadingZerosNonceSize",
                "intrinsicGas" : "0x00"
            },
            "EIP150" : {
                "exception" : "LeadingZerosNonceSize",
                "intrinsicGas" : "0x00"
            },
            "EIP158" : {
                "exception" : "LeadingZerosNonceSize",
                "intrinsicGas" : "0x00"
            },
            "Frontier" : {
                "exception" : "LeadingZerosNonceSize",
                "intrinsicGas" : "0x00"
            },
            "Homestead" : {
                "exception" : "LeadingZerosNonceSize",
                "intrinsicGas" : "0x00"
            },
            "Istanbul" : {
                "exception" : "LeadingZerosNonceSize",
                "intrinsicGas" : "0x00"
            },
            "London" : {
                "exception" : "LeadingZerosNonceSize",
                "intrinsicGas" : "0x00"
            },
            "Paris" : {
                "exception" : "LeadingZerosNonceSize",
                "intrinsicGas" : "0x00"
            },
            "Shanghai" : {
                "exception" : "LeadingZerosNonceSize",
                "intrinsicGas" : "0x00"
            }
        },
        "txbytes" : "0xf86081000182520894b94f5374fce5edbc8e2a8697c15331677e6ebf0b0a801ca098ff921201554726367d2be8c804a7ff89ccf285ebc57dff8ae4c44b9c19ac4aa08887321be575c8095f789dd4c743dfe42c1820f9231f98a962b210e3ac2452a3"
    }
}