{
    "callcallcallcode_ABCB_RECURSIVE" : {
        "env" : {
            "currentCoinbase" : "2adc25665018aa1fe0e6bc666dac8fc2697ff9ba",
            "currentDifficulty" : "0x20000",
            "currentGasLimit" : "0xb2d05e00",
            "currentNumber" : "0x01",
            "currentTimestamp" : "0x03e8",
            "previousHash" : "5e20a0453cecd065ea59c37ac63e079ee08998b6045136a8ce6635c7912ec0b6"
        },
        "post" : {
            "EIP150" : [
                {
                    "hash" : "00aefdf2557f665cdb2328e30a9e703985b5c427ad9a24e111b9bd36b8c73571",
                    "indexes" : {
                        "data" : 0,
                        "gas" : 0,
                        "value" : 0
                    }
                }
            ],
            "EIP158" : [
                {
                    "hash" : "00aefdf2557f665cdb2328e30a9e703985b5c427ad9a24e111b9bd36b8c73571",
                    "indexes" : {
                        "data" : 0,
                        "gas" : 0,
                        "value" : 0
                    }
                }
            ],
            "Frontier" : [
                {
                    "hash" : "57f5cb02223fc5088ccf1424e7f6580dbf33736871eb6e21dbe935a25cb8fcce",
                    "indexes" : {
                        "data" : 0,
                        "gas" : 0,
                        "value" : 0
                    }
                }
            ],
            "Homestead" : [
                {
                    "hash" : "4147efecb96df3d57d5ca561c9c2d56d454908d62cdfcce7eaeecc06f674a15c",
                    "indexes" : {
                        "data" : 0,
                        "gas" : 0,
                        "value" : 0
                    }
                }
            ],
            "Metropolis" : [
                {
                    "hash" : "00aefdf2557f665cdb2328e30a9e703985b5c427ad9a24e111b9bd36b8c73571",
                    "indexes" : {
                        "data" : 0,
                        "gas" : 0,
                        "value" : 0
                    }
                }
            ]
        },
        "pre" : {
            "1000000000000000000000000000000000000000" : {
                "balance" : "0x0de0b6b3a7640000",
                "code" : "0x6040600060406000600073100000000000000000000000000000000000000163017d7840f2600055",
                "nonce" : "0x00",
                "storage" : {
                }
            },
            "1000000000000000000000000000000000000001" : {
                "balance" : "0x02540be400",
                "code" : "0x60406000604060006000731000000000000000000000000000000000000002620f4240f2600155",
                "nonce" : "0x00",
                "storage" : {
                }
            },
            "1000000000000000000000000000000000000002" : {
                "balance" : "0x02540be400",
                "code" : "0x60406000604060007310000000000000000000000000000000000000016207a120f4600255",
                "nonce" : "0x00",
                "storage" : {
                }
            },
            "a94f5374fce5edbc8e2a8697c15331677e6ebf0b" : {
                "balance" : "0x0de0b6b3a7640000",
                "code" : "0x",
                "nonce" : "0x00",
                "storage" : {
                }
            }
        },
        "transaction" : {
            "data" : [
                ""
            ],
            "gasLimit" : [
                "30000000"
            ],
            "gasPrice" : "0x01",
            "nonce" : "0x00",
            "secretKey" : "45a915e4d060149eb4365960e6a7a45f334393093061116b197e3240065ff2d8",
            "to" : "1000000000000000000000000000000000000000",
            "value" : [
                "0"
            ]
        }
    }
}