{
    "EOF1_dataloadn_truncated" : {
        "_info" : {
            "comment" : "",
            "filling-rpc-server" : "evmone-t8n 0.13.0-23+commit.71e2311c",
            "filling-tool-version" : "retesteth-0.3.2-legacy+commit.c1fb07e8.Linux.g++",
            "generatedTestHash" : "a94fefa69441564cd786716abc67e0e7e8754a6a23862221f8eea63cb46af56e",
            "lllcversion" : "Error getting LLLC Version",
            "solidity" : "Error getting solc Version",
            "source" : "src/EOFTestsFiller/efValidation/EOF1_dataloadn_truncated_Copier.json",
            "sourceHash" : "ebc70de1c02600510a194ac168f871fd358bdcfd871f8b85eb0b8a98cf978289"
        },
        "vectors" : {
            "EOF1_dataloadn_truncated_0" : {
                "code" : "0xef000101000402000100010400000000800000d1",
                "results" : {
                    "Osaka" : {
                        "exception" : "EOF_TruncatedImmediate",
                        "result" : false
                    },
                    "Prague" : {
                        "exception" : "EOF_TruncatedImmediate",
                        "result" : false
                    }
                }
            },
            "EOF1_dataloadn_truncated_1" : {
                "code" : "0xef000101000402000100020400000000800000d100",
                "results" : {
                    "Osaka" : {
                        "exception" : "EOF_TruncatedImmediate",
                        "result" : false
                    },
                    "Prague" : {
                        "exception" : "EOF_TruncatedImmediate",
                        "result" : false
                    }
                }
            }
        }
    }
}